tissue_properties/__init__.py
tissue_properties/base_classes.py
tissue_properties/cli.py
tissue_properties/exceptions.py
tissue_properties/units.py
tissue_properties/optical/absorption_coefficient/mainster/__init__.py
tissue_properties/optical/absorption_coefficient/mainster/choroid.py
tissue_properties/optical/absorption_coefficient/mainster/mua-mainster-choroid.txt
tissue_properties/optical/absorption_coefficient/mainster/mua-mainster-rpe.txt
tissue_properties/optical/absorption_coefficient/mainster/reference.py
tissue_properties/optical/absorption_coefficient/mainster/rpe.py
tissue_properties/optical/absorption_coefficient/schulmeister/__init__.py
tissue_properties/optical/absorption_coefficient/schulmeister/blood.py
tissue_properties/optical/absorption_coefficient/schulmeister/choroid.py
tissue_properties/optical/absorption_coefficient/schulmeister/henles_fiber_layer.py
tissue_properties/optical/absorption_coefficient/schulmeister/macular_pigment.py
tissue_properties/optical/absorption_coefficient/schulmeister/melanin.py
tissue_properties/optical/absorption_coefficient/schulmeister/reference.py
tissue_properties/optical/absorption_coefficient/schulmeister/rpe.py
tissue_properties/optical/ocular_transmission/cie203/__init__.py
tissue_properties/optical/ocular_transmission/cie203/direct_transmission-human_eye-cie203_2012.txt
tissue_properties/optical/ocular_transmission/cie203/direct_transmission.py
tissue_properties/optical/ocular_transmission/cie203/reference.py
tissue_properties/optical/ocular_transmission/cie203/total_transmission-human_eye-cie203_2012.txt
tissue_properties/optical/ocular_transmission/cie203/total_transmission.py
tissue_properties/optical/ocular_transmission/mainster/__init__.py
tissue_properties/optical/ocular_transmission/mainster/reference.py
tissue_properties/optical/ocular_transmission/mainster/transmission-human_eye-mainster.txt
tissue_properties/optical/ocular_transmission/mainster/transmission.py
tissue_properties-0.3.0.dist-info/METADATA
tissue_properties-0.3.0.dist-info/WHEEL
tissue_properties-0.3.0.dist-info/entry_points.txt
tissue_properties-0.3.0.dist-info/RECORD
