Metadata-Version: 2.4
Name: tissue-properties
Version: 0.3.0
Summary: A python library for computing/looking up various tissue properties used in laser bioeffect models.
Author-email: CD Clark III <clifton.clark@gmail.com>
Requires-Python: >=3.12
Requires-Dist: numpy>=2.0
Requires-Dist: pint>=0.24.4
Requires-Dist: scipy>=1.14.1
Requires-Dist: thefuzz>=0.22.1
Requires-Dist: typer>=0.13.1
